<templateSet group="PHP class functions">
  <template name="prif" value="private function $NAME$($PARAMETERS$)&#10;{&#10;    $END$&#10;}" description="private function" toReformat="true" toShortenFQNames="true">
    <variable name="NAME" expression="" defaultValue="" alwaysStopAt="true" />
    <variable name="PARAMETERS" expression="phpVar" defaultValue="" alwaysStopAt="true" />
    <context>
      <option name="PHP Class Member" value="true" />
      <option name="PHP Trait Member" value="true" />
    </context>
  </template>
  <template name="prifa" value="private function $NAME$($PARAMETERS$): array&#10;{&#10;    $END$&#10;}" description="private function (returns array)" toReformat="true" toShortenFQNames="true">
    <variable name="NAME" expression="" defaultValue="" alwaysStopAt="true" />
    <variable name="PARAMETERS" expression="phpVar" defaultValue="" alwaysStopAt="true" />
    <context>
      <option name="PHP Class Member" value="true" />
      <option name="PHP Trait Member" value="true" />
    </context>
  </template>
  <template name="prifb" value="private function $NAME$($PARAMETERS$): bool&#10;{&#10;    $END$&#10;}" description="private function (returns bool value)" toReformat="true" toShortenFQNames="true">
    <variable name="NAME" expression="" defaultValue="" alwaysStopAt="true" />
    <variable name="PARAMETERS" expression="phpVar" defaultValue="" alwaysStopAt="true" />
    <context>
      <option name="PHP Class Member" value="true" />
      <option name="PHP Trait Member" value="true" />
    </context>
  </template>
  <template name="priff" value="private function $NAME$($PARAMETERS$): float&#10;{&#10;    $END$&#10;}" description="private function (returns float value)" toReformat="true" toShortenFQNames="true">
    <variable name="NAME" expression="" defaultValue="" alwaysStopAt="true" />
    <variable name="PARAMETERS" expression="phpVar" defaultValue="" alwaysStopAt="true" />
    <context>
      <option name="PHP Class Member" value="true" />
      <option name="PHP Trait Member" value="true" />
    </context>
  </template>
  <template name="prifi" value="private function $NAME$($PARAMETERS$): int&#10;{&#10;    $END$&#10;}" description="private function (returns int value)" toReformat="true" toShortenFQNames="true">
    <variable name="NAME" expression="" defaultValue="" alwaysStopAt="true" />
    <variable name="PARAMETERS" expression="phpVar" defaultValue="" alwaysStopAt="true" />
    <context>
      <option name="PHP Class Member" value="true" />
      <option name="PHP Trait Member" value="true" />
    </context>
  </template>
  <template name="prifs" value="private function $NAME$($PARAMETERS$): string&#10;{&#10;    $END$&#10;}" description="private function (returns string value)" toReformat="true" toShortenFQNames="true">
    <variable name="NAME" expression="" defaultValue="" alwaysStopAt="true" />
    <variable name="PARAMETERS" expression="phpVar" defaultValue="" alwaysStopAt="true" />
    <context>
      <option name="PHP Class Member" value="true" />
      <option name="PHP Trait Member" value="true" />
    </context>
  </template>
  <template name="prifv" value="private function $NAME$($PARAMETERS$): void&#10;{&#10;    $END$&#10;}" description="private function (returns void)" toReformat="true" toShortenFQNames="true">
    <variable name="NAME" expression="" defaultValue="" alwaysStopAt="true" />
    <variable name="PARAMETERS" expression="phpVar" defaultValue="" alwaysStopAt="true" />
    <context>
      <option name="PHP Class Member" value="true" />
      <option name="PHP Trait Member" value="true" />
    </context>
  </template>
  <template name="prof" value="protected function $NAME$($PARAMETERS$)&#10;{&#10;    $END$&#10;}" description="protected function" toReformat="true" toShortenFQNames="true">
    <variable name="NAME" expression="" defaultValue="" alwaysStopAt="true" />
    <variable name="PARAMETERS" expression="phpVar" defaultValue="" alwaysStopAt="true" />
    <context>
      <option name="PHP Class Member" value="true" />
      <option name="PHP Trait Member" value="true" />
    </context>
  </template>
  <template name="profa" value="protected function $NAME$($PARAMETERS$): array&#10;{&#10;    $END$&#10;}" description="protected function (returns array)" toReformat="true" toShortenFQNames="true">
    <variable name="NAME" expression="" defaultValue="" alwaysStopAt="true" />
    <variable name="PARAMETERS" expression="phpVar" defaultValue="" alwaysStopAt="true" />
    <context>
      <option name="PHP Class Member" value="true" />
      <option name="PHP Trait Member" value="true" />
    </context>
  </template>
  <template name="profb" value="protected function $NAME$($PARAMETERS$): bool&#10;{&#10;    $END$&#10;}" description="protected function (returns bool value)" toReformat="true" toShortenFQNames="true">
    <variable name="NAME" expression="" defaultValue="" alwaysStopAt="true" />
    <variable name="PARAMETERS" expression="phpVar" defaultValue="" alwaysStopAt="true" />
    <context>
      <option name="PHP Class Member" value="true" />
      <option name="PHP Trait Member" value="true" />
    </context>
  </template>
  <template name="proff" value="protected function $NAME$($PARAMETERS$): float&#10;{&#10;    $END$&#10;}" description="protected function (returns float value)" toReformat="true" toShortenFQNames="true">
    <variable name="NAME" expression="" defaultValue="" alwaysStopAt="true" />
    <variable name="PARAMETERS" expression="phpVar" defaultValue="" alwaysStopAt="true" />
    <context>
      <option name="PHP Class Member" value="true" />
      <option name="PHP Trait Member" value="true" />
    </context>
  </template>
  <template name="profi" value="protected function $NAME$($PARAMETERS$): int&#10;{&#10;    $END$&#10;}" description="protected function (returns int value)" toReformat="true" toShortenFQNames="true">
    <variable name="NAME" expression="" defaultValue="" alwaysStopAt="true" />
    <variable name="PARAMETERS" expression="phpVar" defaultValue="" alwaysStopAt="true" />
    <context>
      <option name="PHP Class Member" value="true" />
      <option name="PHP Trait Member" value="true" />
    </context>
  </template>
  <template name="profs" value="protected function $NAME$($PARAMETERS$): string&#10;{&#10;    $END$&#10;}" description="protected function (returns string value)" toReformat="true" toShortenFQNames="true">
    <variable name="NAME" expression="" defaultValue="" alwaysStopAt="true" />
    <variable name="PARAMETERS" expression="phpVar" defaultValue="" alwaysStopAt="true" />
    <context>
      <option name="PHP Class Member" value="true" />
      <option name="PHP Trait Member" value="true" />
    </context>
  </template>
  <template name="profv" value="protected function $NAME$($PARAMETERS$): void&#10;{&#10;    $END$&#10;}" description="protected function (returns void)" toReformat="true" toShortenFQNames="true">
    <variable name="NAME" expression="" defaultValue="" alwaysStopAt="true" />
    <variable name="PARAMETERS" expression="phpVar" defaultValue="" alwaysStopAt="true" />
    <context>
      <option name="PHP Class Member" value="true" />
      <option name="PHP Trait Member" value="true" />
    </context>
  </template>
  <template name="pubf" value="public function $NAME$($PARAMETERS$)&#10;{&#10;    $END$&#10;}" description="public function" toReformat="true" toShortenFQNames="true">
    <variable name="NAME" expression="" defaultValue="" alwaysStopAt="true" />
    <variable name="PARAMETERS" expression="phpVar" defaultValue="" alwaysStopAt="true" />
    <context>
      <option name="PHP Class Member" value="true" />
      <option name="PHP Trait Member" value="true" />
    </context>
  </template>
  <template name="pubfa" value="public function $NAME$($PARAMETERS$): array&#10;{&#10;    $END$&#10;}" description="public function (returns array)" toReformat="true" toShortenFQNames="true">
    <variable name="NAME" expression="" defaultValue="" alwaysStopAt="true" />
    <variable name="PARAMETERS" expression="phpVar" defaultValue="" alwaysStopAt="true" />
    <context>
      <option name="PHP Class Member" value="true" />
      <option name="PHP Trait Member" value="true" />
    </context>
  </template>
  <template name="pubfb" value="public function $NAME$($PARAMETERS$): bool&#10;{&#10;    $END$&#10;}" description="public function (returns bool value)" toReformat="true" toShortenFQNames="true">
    <variable name="NAME" expression="" defaultValue="" alwaysStopAt="true" />
    <variable name="PARAMETERS" expression="phpVar" defaultValue="" alwaysStopAt="true" />
    <context>
      <option name="PHP Class Member" value="true" />
      <option name="PHP Trait Member" value="true" />
    </context>
  </template>
  <template name="pubff" value="public function $NAME$($PARAMETERS$): float&#10;{&#10;    $END$&#10;}" description="public function (returns float value)" toReformat="true" toShortenFQNames="true">
    <variable name="NAME" expression="" defaultValue="" alwaysStopAt="true" />
    <variable name="PARAMETERS" expression="phpVar" defaultValue="" alwaysStopAt="true" />
    <context>
      <option name="PHP Class Member" value="true" />
      <option name="PHP Trait Member" value="true" />
    </context>
  </template>
  <template name="pubfi" value="public function $NAME$($PARAMETERS$): int&#10;{&#10;    $END$&#10;}" description="public function (returns int value)" toReformat="true" toShortenFQNames="true">
    <variable name="NAME" expression="" defaultValue="" alwaysStopAt="true" />
    <variable name="PARAMETERS" expression="phpVar" defaultValue="" alwaysStopAt="true" />
    <context>
      <option name="PHP Class Member" value="true" />
      <option name="PHP Trait Member" value="true" />
    </context>
  </template>
  <template name="pubfs" value="public function $NAME$($PARAMETERS$): string&#10;{&#10;    $END$&#10;}" description="public function (returns string value)" toReformat="true" toShortenFQNames="true">
    <variable name="NAME" expression="" defaultValue="" alwaysStopAt="true" />
    <variable name="PARAMETERS" expression="phpVar" defaultValue="" alwaysStopAt="true" />
    <context>
      <option name="PHP Class Member" value="true" />
      <option name="PHP Trait Member" value="true" />
    </context>
  </template>
  <template name="pubfv" value="public function $NAME$($PARAMETERS$): void&#10;{&#10;    $END$&#10;}" description="public function (returns void)" toReformat="true" toShortenFQNames="true">
    <variable name="NAME" expression="" defaultValue="" alwaysStopAt="true" />
    <variable name="PARAMETERS" expression="phpVar" defaultValue="" alwaysStopAt="true" />
    <context>
      <option name="PHP Class Member" value="true" />
      <option name="PHP Trait Member" value="true" />
    </context>
  </template>
  <template name="prift" value="private function $NAME$($PARAMETERS$): $RETURN_TYPE$&#10;{&#10;    $END$&#10;}" description="private function (returns specified type)" toReformat="true" toShortenFQNames="true">
    <variable name="NAME" expression="" defaultValue="" alwaysStopAt="true" />
    <variable name="PARAMETERS" expression="phpVar" defaultValue="" alwaysStopAt="true" />
    <variable name="RETURN_TYPE" expression="" defaultValue="" alwaysStopAt="true" />
    <context>
      <option name="PHP Class Member" value="true" />
      <option name="PHP Trait Member" value="true" />
    </context>
  </template>
  <template name="pubft" value="public function $NAME$($PARAMETERS$): $RETURN_TYPE$&#10;{&#10;    $END$&#10;}" description="public function (returns specified type)" toReformat="true" toShortenFQNames="true">
    <variable name="NAME" expression="" defaultValue="" alwaysStopAt="true" />
    <variable name="PARAMETERS" expression="phpVar" defaultValue="" alwaysStopAt="true" />
    <variable name="RETURN_TYPE" expression="" defaultValue="" alwaysStopAt="true" />
    <context>
      <option name="PHP Class Member" value="true" />
      <option name="PHP Trait Member" value="true" />
    </context>
  </template>
  <template name="proft" value="protected function $NAME$($PARAMETERS$): $RETURN_TYPE$&#10;{&#10;    $END$&#10;}" description="protected function (returns specified type)" toReformat="true" toShortenFQNames="true">
    <variable name="NAME" expression="" defaultValue="" alwaysStopAt="true" />
    <variable name="PARAMETERS" expression="phpVar" defaultValue="" alwaysStopAt="true" />
    <variable name="RETURN_TYPE" expression="" defaultValue="" alwaysStopAt="true" />
    <context>
      <option name="PHP Class Member" value="true" />
      <option name="PHP Trait Member" value="true" />
    </context>
  </template>
  <template name="prifse" value="private function $NAME$($PARAMETERS$): self&#10;{&#10;    $END$&#10;}" description="private function (returns self)" toReformat="true" toShortenFQNames="true">
    <variable name="NAME" expression="" defaultValue="" alwaysStopAt="true" />
    <variable name="PARAMETERS" expression="phpVar" defaultValue="" alwaysStopAt="true" />
    <context>
      <option name="PHP Class Member" value="true" />
      <option name="PHP Trait Member" value="true" />
    </context>
  </template>
  <template name="profse" value="protected function $NAME$($PARAMETERS$): self&#10;{&#10;    $END$&#10;}" description="protected function (returns self)" toReformat="true" toShortenFQNames="true">
    <variable name="NAME" expression="" defaultValue="" alwaysStopAt="true" />
    <variable name="PARAMETERS" expression="phpVar" defaultValue="" alwaysStopAt="true" />
    <context>
      <option name="PHP Class Member" value="true" />
      <option name="PHP Trait Member" value="true" />
    </context>
  </template>
  <template name="pubfse" value="public function $NAME$($PARAMETERS$): self&#10;{&#10;    $END$&#10;}" description="public function (returns self)" toReformat="true" toShortenFQNames="true">
    <variable name="NAME" expression="" defaultValue="" alwaysStopAt="true" />
    <variable name="PARAMETERS" expression="phpVar" defaultValue="" alwaysStopAt="true" />
    <context>
      <option name="PHP Class Member" value="true" />
      <option name="PHP Trait Member" value="true" />
    </context>
  </template>
  <template name="prifst" value="private function $NAME$($PARAMETERS$): static&#10;{&#10;    $END$&#10;}" description="private function (returns static)" toReformat="true" toShortenFQNames="true">
    <variable name="NAME" expression="" defaultValue="" alwaysStopAt="true" />
    <variable name="PARAMETERS" expression="phpVar" defaultValue="" alwaysStopAt="true" />
    <context>
      <option name="PHP Class Member" value="true" />
      <option name="PHP Trait Member" value="true" />
    </context>
  </template>
  <template name="profst" value="protected function $NAME$($PARAMETERS$): static&#10;{&#10;    $END$&#10;}" description="protected function (returns static)" toReformat="true" toShortenFQNames="true">
    <variable name="NAME" expression="" defaultValue="" alwaysStopAt="true" />
    <variable name="PARAMETERS" expression="phpVar" defaultValue="" alwaysStopAt="true" />
    <context>
      <option name="PHP Class Member" value="true" />
      <option name="PHP Trait Member" value="true" />
    </context>
  </template>
  <template name="pubfst" value="public function $NAME$($PARAMETERS$): static&#10;{&#10;    $END$&#10;}" description="public function (returns static)" toReformat="true" toShortenFQNames="true">
    <variable name="NAME" expression="" defaultValue="" alwaysStopAt="true" />
    <variable name="PARAMETERS" expression="phpVar" defaultValue="" alwaysStopAt="true" />
    <context>
      <option name="PHP Class Member" value="true" />
      <option name="PHP Trait Member" value="true" />
    </context>
  </template>
</templateSet>